datengeist/Sample_Dataset.py
datengeist/__init__.py
datengeist/start.py
datengeist/assets/git_images/Screenshot from 2024-11-13 13-02-23.png
datengeist/assets/git_images/Screenshot from 2024-11-13 13-02-35.png
datengeist/assets/git_images/Screenshot from 2024-11-13 13-02-46.png
datengeist/assets/git_images/Screenshot from 2024-11-13 13-03-58.png
datengeist/assets/git_images/Screenshot from 2024-11-13 13-04-22.png
datengeist/assets/logo/logo.png
datengeist/config/config.py
datengeist/pages/1_General_Info.py
datengeist/pages/2_Feature_Info.py
datengeist/pages/3_Relate_Features.py
datengeist/utils/calc.py
datengeist/utils/constants.py
datengeist/utils/feature_tools.py
datengeist/utils/helper.py
datengeist/utils/session_control.py
datengeist/utils/style.py
datengeist/visual/comparison_chart.py
datengeist/visual/corr_chart.py
datengeist/visual/distribution_chart.py
datengeist/visual/missing_value.py
datengeist-0.0.2.dist-info/LICENSE
datengeist-0.0.2.dist-info/METADATA
datengeist-0.0.2.dist-info/WHEEL
datengeist-0.0.2.dist-info/entry_points.txt
datengeist-0.0.2.dist-info/top_level.txt
datengeist-0.0.2.dist-info/RECORD
