Metadata-Version: 2.1
Name: datengeist
Version: 0.0.2
Summary: Application for easy understanding of unstructured data
Home-page: https://github.com/alienobserver/datengeist
Author: Narek Aristakesyan
Author-email: aristakesyannarek11@gmail.com
License: Apache License 2.0
Classifier: Development Status :: 1 - Planning
Classifier: Intended Audience :: Science/Research
Classifier: License :: OSI Approved :: Apache Software License
Classifier: Operating System :: POSIX :: Linux
Classifier: Programming Language :: Python :: 3.11
License-File: LICENSE
Requires-Dist: pandas~=2.2.3
Requires-Dist: streamlit~=1.39.0
Requires-Dist: numpy~=2.1.2
Requires-Dist: scipy~=1.14.1
Requires-Dist: opencv-python~=4.10.0.84
Requires-Dist: pillow~=10.4.0
Requires-Dist: plotly~=5.24.1
Requires-Dist: setuptools~=68.2.0
Requires-Dist: openpyxl~=3.1.5
